Metadata-Version: 2.1
Name: panda3d_vfs
Version: 1.0.0
Summary: Panda3D module provides easy access to the virtual file system capabilities of Panda3D
Home-page: https://github.com/NxtStudios/panda3d-vfs
Author: Jordan Maxwell
Maintainer: Jordan Maxwell
License: MIT
Classifier: Programming Language :: Python :: 3
License-File: LICENSE
